bitproto/__init__.py
bitproto/_ast.py
bitproto/_main.py
bitproto/errors.py
bitproto/grammars.py
bitproto/lexer.py
bitproto/linter.py
bitproto/options.py
bitproto/parser.py
bitproto/utils.py
bitproto/renderer/__init__.py
bitproto/renderer/block.py
bitproto/renderer/formatter.py
bitproto/renderer/renderer.py
bitproto/renderer/impls/__init__.py
bitproto/renderer/impls/c/__init__.py
bitproto/renderer/impls/c/formatter.py
bitproto/renderer/impls/c/renderer_c.py
bitproto/renderer/impls/c/renderer_h.py
bitproto/renderer/impls/go/__init__.py
bitproto/renderer/impls/go/formatter.py
bitproto/renderer/impls/go/renderer.py
bitproto/renderer/impls/py/__init__.py
bitproto/renderer/impls/py/formatter.py
bitproto/renderer/impls/py/renderer.py
bitproto-0.4.1.dist-info/METADATA
bitproto-0.4.1.dist-info/WHEEL
bitproto-0.4.1.dist-info/entry_points.txt
bitproto-0.4.1.dist-info/top_level.txt
bitproto-0.4.1.dist-info/RECORD
