Metadata-Version: 2.1
Name: bitproto
Version: 0.4.1
Summary: bit level data interchange format.
Home-page: https://github.com/hit9/bitproto
Author: Chao Wang
Author-email: hit9@icloud.com
License: UNKNOWN
Platform: UNKNOWN
Classifier: Development Status :: 2 - Pre-Alpha
Classifier: Environment :: Console
Classifier: Intended Audience :: Developers
Classifier: License :: OSI Approved :: BSD License
Classifier: Operating System :: OS Independent
Classifier: Programming Language :: Python
Classifier: Programming Language :: Python :: 3.7
Classifier: Programming Language :: Python :: 3.8
Classifier: Programming Language :: Python :: 3.9
Requires-Python: >=3.7
Requires-Dist: ply (>=3.11)
Requires-Dist: typing-extensions (>=3.6.0)
